api/__init__.py
api/auth.py
api/main.py
api/models.py
api/routes/__init__.py
api/routes/algorithm_routes.py
api/routes/auth_routes.py
api/routes/teleport_routes.py
db/__init__.py
db/crud.py
db/database.py
db/models.py
quantumflow/__init__.py
quantumflow/algorithms/__init__.py
quantumflow/algorithms/compression/__init__.py
quantumflow/algorithms/compression/amplitude_amplification.py
quantumflow/algorithms/compression/qft_compression.py
quantumflow/algorithms/compression/token_compression.py
quantumflow/algorithms/cryptography/__init__.py
quantumflow/algorithms/cryptography/qkd.py
quantumflow/algorithms/cryptography/qrng.py
quantumflow/algorithms/machine_learning/__init__.py
quantumflow/algorithms/machine_learning/qnn.py
quantumflow/algorithms/machine_learning/qsvm.py
quantumflow/algorithms/machine_learning/vqe.py
quantumflow/algorithms/optimization/__init__.py
quantumflow/algorithms/optimization/grover.py
quantumflow/algorithms/optimization/qaoa.py
quantumflow/algorithms/optimization/quantum_annealing.py
quantumflow/algorithms/utility/__init__.py
quantumflow/algorithms/utility/circuit_optimizer.py
quantumflow/algorithms/utility/error_correction.py
quantumflow/api/__init__.py
quantumflow/api/routes/__init__.py
quantumflow/api/routes/billing_routes.py
quantumflow/api/routes/workflow_routes.py
quantumflow/backends/__init__.py
quantumflow/backends/base_backend.py
quantumflow/backends/braket_backend.py
quantumflow/backends/ibm_backend.py
quantumflow/backends/simulator_backend.py
quantumflow/billing/__init__.py
quantumflow/billing/models.py
quantumflow/billing/stripe_service.py
quantumflow/core/__init__.py
quantumflow/core/entanglement.py
quantumflow/core/memory.py
quantumflow/core/quantum_backprop.py
quantumflow/core/quantum_compressor.py
quantumflow/core/teleportation.py
quantumflow/core/workflow.py
quantumflow/integrations/__init__.py
quantumflow/integrations/autogen_tools.py
quantumflow/integrations/crewai_agents.py
quantumflow/integrations/crewai_tools.py
quantumflow_sdk-0.3.0.dist-info/METADATA
quantumflow_sdk-0.3.0.dist-info/WHEEL
quantumflow_sdk-0.3.0.dist-info/entry_points.txt
quantumflow_sdk-0.3.0.dist-info/top_level.txt
quantumflow_sdk-0.3.0.dist-info/RECORD
