Metadata-Version: 2.4
Name: quantumflow-sdk
Version: 0.3.0
Summary: Quantum-optimized AI agent workflow platform with 53% token compression
Author-email: BlockQuantAI <hello@blockquant.ai>
License-Expression: MIT
Project-URL: Homepage, https://qflowai.dev
Project-URL: Documentation, https://qflowai.dev/docs
Project-URL: Repository, https://github.com/blockquantai/quantumflow
Project-URL: Issues, https://github.com/blockquantai/quantumflow/issues
Keywords: quantum,quantum-computing,ai,machine-learning,token-compression,qkd,teleportation,langchain,crewai
Classifier: Development Status :: 4 - Beta
Classifier: Intended Audience :: Developers
Classifier: Intended Audience :: Science/Research
Classifier: Operating System :: OS Independent
Classifier: Programming Language :: Python :: 3
Classifier: Programming Language :: Python :: 3.9
Classifier: Programming Language :: Python :: 3.10
Classifier: Programming Language :: Python :: 3.11
Classifier: Programming Language :: Python :: 3.12
Classifier: Topic :: Scientific/Engineering :: Artificial Intelligence
Classifier: Topic :: Scientific/Engineering :: Physics
Requires-Python: >=3.9
Requires-Dist: numpy>=1.21.0
Requires-Dist: scipy>=1.7.0
Provides-Extra: ibm
Requires-Dist: qiskit>=0.45.0; extra == "ibm"
Requires-Dist: qiskit-ibm-runtime>=0.15.0; extra == "ibm"
Provides-Extra: aws
Requires-Dist: amazon-braket-sdk>=1.50.0; extra == "aws"
Provides-Extra: langchain
Requires-Dist: langchain>=0.1.0; extra == "langchain"
Provides-Extra: crewai
Requires-Dist: crewai>=0.1.0; extra == "crewai"
Provides-Extra: all
Requires-Dist: qiskit>=0.45.0; extra == "all"
Requires-Dist: qiskit-ibm-runtime>=0.15.0; extra == "all"
Requires-Dist: amazon-braket-sdk>=1.50.0; extra == "all"
Requires-Dist: langchain>=0.1.0; extra == "all"
Requires-Dist: crewai>=0.1.0; extra == "all"
Provides-Extra: dev
Requires-Dist: pytest>=7.0.0; extra == "dev"
Requires-Dist: pytest-asyncio>=0.21.0; extra == "dev"
Requires-Dist: black>=23.0.0; extra == "dev"
Requires-Dist: ruff>=0.1.0; extra == "dev"
